{
  "schema_version": 4,
  "id": "bazi-calendar-1924-2044-v2-current",
  "chart_type": "bazi",
  "kind": "calendar_sample_frequency",
  "label": "1924立春—2044立春历法样本",
  "start": "1924-02-05T09:49:32+08:00",
  "end": "2044-02-04T12:43:35+08:00",
  "timezone": "Asia/Shanghai",
  "day_boundary": "current",
  "config_id": "bazi-sxtwl-2.0.7-asia-shanghai-current-v1",
  "engine": "sxtwl 2.0.7",
  "rules_version": "shensha-2026.07-v2.1",
  "rules_registry_hash": "sha256:3d0f8f85d67e66b40927c19ca3f39b53b7f49aa3eb91121e9dad92c5a0e5b096",
  "feature_catalog": [
    "bazi.shensha.ciguan",
    "bazi.shensha.dexiu",
    "bazi.shensha.fuxing",
    "bazi.shensha.guasuo",
    "bazi.shensha.guchen",
    "bazi.shensha.guoyin",
    "bazi.shensha.hongluan",
    "bazi.shensha.hongyan",
    "bazi.shensha.huagai",
    "bazi.shensha.jiangxing",
    "bazi.shensha.jiesha",
    "bazi.shensha.jinyu",
    "bazi.shensha.kuigang",
    "bazi.shensha.lushen",
    "bazi.shensha.taiji",
    "bazi.shensha.taohua",
    "bazi.shensha.ten_bad_defeats",
    "bazi.shensha.tiande",
    "bazi.shensha.tianku",
    "bazi.shensha.tianxi",
    "bazi.shensha.tianyi",
    "bazi.shensha.tianyi_doctor",
    "bazi.shensha.wangshen",
    "bazi.shensha.wenchang",
    "bazi.shensha.xuetang",
    "bazi.shensha.yangren",
    "bazi.shensha.yima",
    "bazi.shensha.yinyang_error",
    "bazi.shensha.yuede",
    "bazi.shensha.zaisha"
  ],
  "feature_catalog_hash": "sha256:9a0a48fe7b6745c8b33beafa432f466e655059308238667120b34b8c78e025e0",
  "unique_state_count": 420815,
  "sample_unit": "minute",
  "weighted_unit": "minute",
  "sample_weight": 63113934.05,
  "method": "按四柱变化边界分段穷举，并按每段实际持续分钟数加权。",
  "features": {
    "bazi.shensha.ciguan": {
      "hit_weight": 3611040.0
    },
    "bazi.shensha.dexiu": {
      "hit_weight": 55488174.05
    },
    "bazi.shensha.fuxing": {
      "hit_weight": 29031910.466667
    },
    "bazi.shensha.guasuo": {
      "hit_weight": 14496780.0
    },
    "bazi.shensha.guchen": {
      "hit_weight": 14504934.05
    },
    "bazi.shensha.guoyin": {
      "hit_weight": 17716260.0
    },
    "bazi.shensha.hongluan": {
      "hit_weight": 14496720.0
    },
    "bazi.shensha.hongyan": {
      "hit_weight": 20170380.0
    },
    "bazi.shensha.huagai": {
      "hit_weight": 42610483.583333
    },
    "bazi.shensha.jiangxing": {
      "hit_weight": 42605994.05
    },
    "bazi.shensha.jiesha": {
      "hit_weight": 24283690.466667
    },
    "bazi.shensha.jinyu": {
      "hit_weight": 17761603.583333
    },
    "bazi.shensha.kuigang": {
      "hit_weight": 4206240.0
    },
    "bazi.shensha.lushen": {
      "hit_weight": 17774754.05
    },
    "bazi.shensha.taiji": {
      "hit_weight": 36277810.466667
    },
    "bazi.shensha.taohua": {
      "hit_weight": 24291643.583333
    },
    "bazi.shensha.ten_bad_defeats": {
      "hit_weight": 10517760.0
    },
    "bazi.shensha.tiande": {
      "hit_weight": 19621260.0
    },
    "bazi.shensha.tianku": {
      "hit_weight": 17764990.466667
    },
    "bazi.shensha.tianxi": {
      "hit_weight": 14500920.0
    },
    "bazi.shensha.tianyi": {
      "hit_weight": 28988220.0
    },
    "bazi.shensha.tianyi_doctor": {
      "hit_weight": 14504580.0
    },
    "bazi.shensha.wangshen": {
      "hit_weight": 24287754.05
    },
    "bazi.shensha.wenchang": {
      "hit_weight": 19367590.466667
    },
    "bazi.shensha.xuetang": {
      "hit_weight": 7690980.0
    },
    "bazi.shensha.yangren": {
      "hit_weight": 19386180.0
    },
    "bazi.shensha.yima": {
      "hit_weight": 23074254.05
    },
    "bazi.shensha.yinyang_error": {
      "hit_weight": 12622860.0
    },
    "bazi.shensha.yuede": {
      "hit_weight": 21785514.05
    },
    "bazi.shensha.zaisha": {
      "hit_weight": 23071494.05
    }
  },
  "theme_comparison_method": "transparent_metric_distributions",
  "theme_metric_weights_by_gender": {
    "male": {
      "事业": {
        "officer_count": {
          "0": 2935680.0,
          "1": 11413810.466667,
          "2": 18720720.0,
          "3": 17200200.0,
          "4": 9458503.583333,
          "5": 2894580.0,
          "6": 458940.0,
          "7": 31500.0
        },
        "resource_count": {
          "0": 3179563.583333,
          "1": 11576170.466667,
          "2": 18283020.0,
          "3": 16869120.0,
          "4": 9633900.0,
          "5": 3017460.0,
          "6": 520140.0,
          "7": 34560.0
        },
        "output_count": {
          "0": 3122520.0,
          "1": 11517780.0,
          "2": 18419400.0,
          "3": 16975123.583333,
          "4": 9534250.466667,
          "5": 3002100.0,
          "6": 507420.0,
          "7": 35340.0
        },
        "relation_count": {
          "0": 839400.0,
          "1": 1663560.0,
          "2": 4165980.0,
          "3": 7044420.0,
          "4": 10012330.466667,
          "5": 11184360.0,
          "6": 10928203.583333,
          "7": 7783260.0,
          "8": 4957320.0,
          "9": 2568540.0,
          "10": 1093440.0,
          "11": 509580.0,
          "12": 205020.0,
          "13": 82800.0,
          "14": 33840.0,
          "15": 27840.0,
          "16": 11280.0,
          "17": 2520.0,
          "18": 240.0
        },
        "mobility_count": {
          "0": 26700900.0,
          "1": 21109390.466667,
          "2": 12588283.583333,
          "3": 2557200.0,
          "4": 121680.0,
          "5": 36480.0
        },
        "shensha_count": {
          "0": 3120.0,
          "1": 117420.0,
          "2": 1068000.0,
          "3": 3865080.0,
          "4": 8700780.0,
          "5": 12870600.0,
          "6": 14132743.583333,
          "7": 11469550.466667,
          "8": 6773460.0,
          "9": 2959800.0,
          "10": 907380.0,
          "11": 219900.0,
          "12": 23460.0,
          "13": 2640.0
        }
      },
      "财富": {
        "visible_wealth_count": {
          "0": 32296560.0,
          "1": 24284034.05,
          "2": 6013020.0,
          "3": 520320.0
        },
        "hidden_wealth_count": {
          "0": 5974740.0,
          "1": 17986320.0,
          "2": 21618120.0,
          "3": 13487934.05,
          "4": 4046820.0
        },
        "output_count": {
          "0": 3122520.0,
          "1": 11517780.0,
          "2": 18419400.0,
          "3": 16975123.583333,
          "4": 9534250.466667,
          "5": 3002100.0,
          "6": 507420.0,
          "7": 35340.0
        },
        "peer_count": {
          "0": 3003480.0,
          "1": 11399143.583333,
          "2": 18695880.0,
          "3": 17178310.466667,
          "4": 9341760.0,
          "5": 2957760.0,
          "6": 495180.0,
          "7": 42420.0
        },
        "relation_count": {
          "0": 582660.0,
          "1": 1328400.0,
          "2": 3706440.0,
          "3": 6333720.0,
          "4": 9291840.0,
          "5": 11151780.0,
          "6": 11390040.0,
          "7": 8519094.05,
          "8": 5431200.0,
          "9": 2991840.0,
          "10": 1287780.0,
          "11": 628740.0,
          "12": 259860.0,
          "13": 101700.0,
          "14": 48120.0,
          "15": 41400.0,
          "16": 15840.0,
          "17": 3480.0
        },
        "shensha_count": {
          "0": 2345760.0,
          "1": 8351160.0,
          "2": 14022840.0,
          "3": 15130080.0,
          "4": 11181643.583333,
          "5": 7085940.0,
          "6": 3666190.466667,
          "7": 1115280.0,
          "8": 197880.0,
          "9": 17160.0
        }
      },
      "感情": {
        "visible_spouse_count": {
          "0": 32296560.0,
          "1": 24284034.05,
          "2": 6013020.0,
          "3": 520320.0
        },
        "hidden_spouse_count": {
          "0": 5974740.0,
          "1": 17986320.0,
          "2": 21618120.0,
          "3": 13487934.05,
          "4": 4046820.0
        },
        "spouse_palace_relation_count": {
          "0": 2114640.0,
          "1": 13470720.0,
          "2": 21300360.0,
          "3": 16529034.05,
          "4": 7116660.0,
          "5": 1959240.0,
          "6": 468840.0,
          "7": 129720.0,
          "8": 18480.0,
          "9": 6240.0
        },
        "day_stem_combine_count": {
          "0": 46019520.0,
          "1": 15330354.05,
          "2": 1700880.0,
          "3": 63180.0
        },
        "relation_count": {
          "0": 170580.0,
          "1": 1083960.0,
          "2": 2613120.0,
          "3": 5301300.0,
          "4": 8306340.0,
          "5": 10545130.466667,
          "6": 11904000.0,
          "7": 9899880.0,
          "8": 6542983.583333,
          "9": 3730020.0,
          "10": 1734960.0,
          "11": 710880.0,
          "12": 322380.0,
          "13": 143280.0,
          "14": 48720.0,
          "15": 29520.0,
          "16": 19920.0,
          "17": 6120.0,
          "18": 840.0
        },
        "shensha_count": {
          "0": 6068940.0,
          "1": 15836650.466667,
          "2": 18349920.0,
          "3": 13836583.583333,
          "4": 6659160.0,
          "5": 2031960.0,
          "6": 311880.0,
          "7": 18840.0
        }
      },
      "健康": {
        "missing_element_count": {
          "0": 51313870.466667,
          "1": 11282383.583333,
          "2": 504060.0,
          "3": 13560.0,
          "4": 60.0
        },
        "concentrated_element_count": {
          "0": 78840.0,
          "1": 6674160.0,
          "2": 30176880.0,
          "3": 24320454.05,
          "4": 1862760.0,
          "5": 840.0
        },
        "root_pillar_count": {
          "0": 6006720.0,
          "1": 17914783.583333,
          "2": 21648970.466667,
          "3": 13509240.0,
          "4": 4034220.0
        },
        "pressure_relation_count": {
          "0": 397740.0,
          "1": 2979600.0,
          "2": 6601500.0,
          "3": 12135240.0,
          "4": 14336983.583333,
          "5": 12274450.466667,
          "6": 7272420.0,
          "7": 3693480.0,
          "8": 1842780.0,
          "9": 809160.0,
          "10": 309480.0,
          "11": 194700.0,
          "12": 137880.0,
          "13": 95160.0,
          "14": 29640.0,
          "15": 3720.0
        },
        "repeated_branch_count": {
          "0": 36164263.583333,
          "1": 25745170.466667,
          "2": 1204500.0
        },
        "shensha_count": {
          "0": 1258560.0,
          "1": 5482740.0,
          "2": 10996500.0,
          "3": 14279383.583333,
          "4": 13738320.0,
          "5": 9856860.0,
          "6": 5026930.466667,
          "7": 1887420.0,
          "8": 490020.0,
          "9": 91560.0,
          "10": 5640.0
        }
      }
    },
    "female": {
      "事业": {
        "officer_count": {
          "0": 2935680.0,
          "1": 11413810.466667,
          "2": 18720720.0,
          "3": 17200200.0,
          "4": 9458503.583333,
          "5": 2894580.0,
          "6": 458940.0,
          "7": 31500.0
        },
        "resource_count": {
          "0": 3179563.583333,
          "1": 11576170.466667,
          "2": 18283020.0,
          "3": 16869120.0,
          "4": 9633900.0,
          "5": 3017460.0,
          "6": 520140.0,
          "7": 34560.0
        },
        "output_count": {
          "0": 3122520.0,
          "1": 11517780.0,
          "2": 18419400.0,
          "3": 16975123.583333,
          "4": 9534250.466667,
          "5": 3002100.0,
          "6": 507420.0,
          "7": 35340.0
        },
        "relation_count": {
          "0": 839400.0,
          "1": 1663560.0,
          "2": 4165980.0,
          "3": 7044420.0,
          "4": 10012330.466667,
          "5": 11184360.0,
          "6": 10928203.583333,
          "7": 7783260.0,
          "8": 4957320.0,
          "9": 2568540.0,
          "10": 1093440.0,
          "11": 509580.0,
          "12": 205020.0,
          "13": 82800.0,
          "14": 33840.0,
          "15": 27840.0,
          "16": 11280.0,
          "17": 2520.0,
          "18": 240.0
        },
        "mobility_count": {
          "0": 26700900.0,
          "1": 21109390.466667,
          "2": 12588283.583333,
          "3": 2557200.0,
          "4": 121680.0,
          "5": 36480.0
        },
        "shensha_count": {
          "0": 3120.0,
          "1": 117420.0,
          "2": 1068000.0,
          "3": 3865080.0,
          "4": 8700780.0,
          "5": 12870600.0,
          "6": 14132743.583333,
          "7": 11469550.466667,
          "8": 6773460.0,
          "9": 2959800.0,
          "10": 907380.0,
          "11": 219900.0,
          "12": 23460.0,
          "13": 2640.0
        }
      },
      "财富": {
        "visible_wealth_count": {
          "0": 32296560.0,
          "1": 24284034.05,
          "2": 6013020.0,
          "3": 520320.0
        },
        "hidden_wealth_count": {
          "0": 5974740.0,
          "1": 17986320.0,
          "2": 21618120.0,
          "3": 13487934.05,
          "4": 4046820.0
        },
        "output_count": {
          "0": 3122520.0,
          "1": 11517780.0,
          "2": 18419400.0,
          "3": 16975123.583333,
          "4": 9534250.466667,
          "5": 3002100.0,
          "6": 507420.0,
          "7": 35340.0
        },
        "peer_count": {
          "0": 3003480.0,
          "1": 11399143.583333,
          "2": 18695880.0,
          "3": 17178310.466667,
          "4": 9341760.0,
          "5": 2957760.0,
          "6": 495180.0,
          "7": 42420.0
        },
        "relation_count": {
          "0": 582660.0,
          "1": 1328400.0,
          "2": 3706440.0,
          "3": 6333720.0,
          "4": 9291840.0,
          "5": 11151780.0,
          "6": 11390040.0,
          "7": 8519094.05,
          "8": 5431200.0,
          "9": 2991840.0,
          "10": 1287780.0,
          "11": 628740.0,
          "12": 259860.0,
          "13": 101700.0,
          "14": 48120.0,
          "15": 41400.0,
          "16": 15840.0,
          "17": 3480.0
        },
        "shensha_count": {
          "0": 2345760.0,
          "1": 8351160.0,
          "2": 14022840.0,
          "3": 15130080.0,
          "4": 11181643.583333,
          "5": 7085940.0,
          "6": 3666190.466667,
          "7": 1115280.0,
          "8": 197880.0,
          "9": 17160.0
        }
      },
      "感情": {
        "visible_spouse_count": {
          "0": 32325370.466667,
          "1": 24204223.583333,
          "2": 6088200.0,
          "3": 496140.0
        },
        "hidden_spouse_count": {
          "0": 6010200.0,
          "1": 17948530.466667,
          "2": 21571260.0,
          "3": 13558963.583333,
          "4": 4024980.0
        },
        "spouse_palace_relation_count": {
          "0": 2114640.0,
          "1": 13470720.0,
          "2": 21300360.0,
          "3": 16529034.05,
          "4": 7116660.0,
          "5": 1959240.0,
          "6": 468840.0,
          "7": 129720.0,
          "8": 18480.0,
          "9": 6240.0
        },
        "day_stem_combine_count": {
          "0": 46019520.0,
          "1": 15330354.05,
          "2": 1700880.0,
          "3": 63180.0
        },
        "relation_count": {
          "0": 170580.0,
          "1": 1083960.0,
          "2": 2613120.0,
          "3": 5301300.0,
          "4": 8306340.0,
          "5": 10545130.466667,
          "6": 11904000.0,
          "7": 9899880.0,
          "8": 6542983.583333,
          "9": 3730020.0,
          "10": 1734960.0,
          "11": 710880.0,
          "12": 322380.0,
          "13": 143280.0,
          "14": 48720.0,
          "15": 29520.0,
          "16": 19920.0,
          "17": 6120.0,
          "18": 840.0
        },
        "shensha_count": {
          "0": 6068940.0,
          "1": 15836650.466667,
          "2": 18349920.0,
          "3": 13836583.583333,
          "4": 6659160.0,
          "5": 2031960.0,
          "6": 311880.0,
          "7": 18840.0
        }
      },
      "健康": {
        "missing_element_count": {
          "0": 51313870.466667,
          "1": 11282383.583333,
          "2": 504060.0,
          "3": 13560.0,
          "4": 60.0
        },
        "concentrated_element_count": {
          "0": 78840.0,
          "1": 6674160.0,
          "2": 30176880.0,
          "3": 24320454.05,
          "4": 1862760.0,
          "5": 840.0
        },
        "root_pillar_count": {
          "0": 6006720.0,
          "1": 17914783.583333,
          "2": 21648970.466667,
          "3": 13509240.0,
          "4": 4034220.0
        },
        "pressure_relation_count": {
          "0": 397740.0,
          "1": 2979600.0,
          "2": 6601500.0,
          "3": 12135240.0,
          "4": 14336983.583333,
          "5": 12274450.466667,
          "6": 7272420.0,
          "7": 3693480.0,
          "8": 1842780.0,
          "9": 809160.0,
          "10": 309480.0,
          "11": 194700.0,
          "12": 137880.0,
          "13": 95160.0,
          "14": 29640.0,
          "15": 3720.0
        },
        "repeated_branch_count": {
          "0": 36164263.583333,
          "1": 25745170.466667,
          "2": 1204500.0
        },
        "shensha_count": {
          "0": 1258560.0,
          "1": 5482740.0,
          "2": 10996500.0,
          "3": 14279383.583333,
          "4": 13738320.0,
          "5": 9856860.0,
          "6": 5026930.466667,
          "7": 1887420.0,
          "8": 490020.0,
          "9": 91560.0,
          "10": 5640.0
        }
      }
    },
    "neutral": {
      "事业": {
        "officer_count": {
          "0": 2935680.0,
          "1": 11413810.466667,
          "2": 18720720.0,
          "3": 17200200.0,
          "4": 9458503.583333,
          "5": 2894580.0,
          "6": 458940.0,
          "7": 31500.0
        },
        "resource_count": {
          "0": 3179563.583333,
          "1": 11576170.466667,
          "2": 18283020.0,
          "3": 16869120.0,
          "4": 9633900.0,
          "5": 3017460.0,
          "6": 520140.0,
          "7": 34560.0
        },
        "output_count": {
          "0": 3122520.0,
          "1": 11517780.0,
          "2": 18419400.0,
          "3": 16975123.583333,
          "4": 9534250.466667,
          "5": 3002100.0,
          "6": 507420.0,
          "7": 35340.0
        },
        "relation_count": {
          "0": 839400.0,
          "1": 1663560.0,
          "2": 4165980.0,
          "3": 7044420.0,
          "4": 10012330.466667,
          "5": 11184360.0,
          "6": 10928203.583333,
          "7": 7783260.0,
          "8": 4957320.0,
          "9": 2568540.0,
          "10": 1093440.0,
          "11": 509580.0,
          "12": 205020.0,
          "13": 82800.0,
          "14": 33840.0,
          "15": 27840.0,
          "16": 11280.0,
          "17": 2520.0,
          "18": 240.0
        },
        "mobility_count": {
          "0": 26700900.0,
          "1": 21109390.466667,
          "2": 12588283.583333,
          "3": 2557200.0,
          "4": 121680.0,
          "5": 36480.0
        },
        "shensha_count": {
          "0": 3120.0,
          "1": 117420.0,
          "2": 1068000.0,
          "3": 3865080.0,
          "4": 8700780.0,
          "5": 12870600.0,
          "6": 14132743.583333,
          "7": 11469550.466667,
          "8": 6773460.0,
          "9": 2959800.0,
          "10": 907380.0,
          "11": 219900.0,
          "12": 23460.0,
          "13": 2640.0
        }
      },
      "财富": {
        "visible_wealth_count": {
          "0": 32296560.0,
          "1": 24284034.05,
          "2": 6013020.0,
          "3": 520320.0
        },
        "hidden_wealth_count": {
          "0": 5974740.0,
          "1": 17986320.0,
          "2": 21618120.0,
          "3": 13487934.05,
          "4": 4046820.0
        },
        "output_count": {
          "0": 3122520.0,
          "1": 11517780.0,
          "2": 18419400.0,
          "3": 16975123.583333,
          "4": 9534250.466667,
          "5": 3002100.0,
          "6": 507420.0,
          "7": 35340.0
        },
        "peer_count": {
          "0": 3003480.0,
          "1": 11399143.583333,
          "2": 18695880.0,
          "3": 17178310.466667,
          "4": 9341760.0,
          "5": 2957760.0,
          "6": 495180.0,
          "7": 42420.0
        },
        "relation_count": {
          "0": 582660.0,
          "1": 1328400.0,
          "2": 3706440.0,
          "3": 6333720.0,
          "4": 9291840.0,
          "5": 11151780.0,
          "6": 11390040.0,
          "7": 8519094.05,
          "8": 5431200.0,
          "9": 2991840.0,
          "10": 1287780.0,
          "11": 628740.0,
          "12": 259860.0,
          "13": 101700.0,
          "14": 48120.0,
          "15": 41400.0,
          "16": 15840.0,
          "17": 3480.0
        },
        "shensha_count": {
          "0": 2345760.0,
          "1": 8351160.0,
          "2": 14022840.0,
          "3": 15130080.0,
          "4": 11181643.583333,
          "5": 7085940.0,
          "6": 3666190.466667,
          "7": 1115280.0,
          "8": 197880.0,
          "9": 17160.0
        }
      },
      "感情": {
        "visible_spouse_count": {
          "0": 13622340.0,
          "1": 27298090.466667,
          "2": 18138523.583333,
          "3": 4054980.0
        },
        "hidden_spouse_count": {
          "0": 684600.0,
          "1": 3603840.0,
          "2": 9609840.0,
          "3": 14740920.0,
          "4": 15279550.466667,
          "5": 10774440.0,
          "6": 5803543.583333,
          "7": 2054040.0,
          "8": 563160.0
        },
        "spouse_palace_relation_count": {
          "0": 2114640.0,
          "1": 13470720.0,
          "2": 21300360.0,
          "3": 16529034.05,
          "4": 7116660.0,
          "5": 1959240.0,
          "6": 468840.0,
          "7": 129720.0,
          "8": 18480.0,
          "9": 6240.0
        },
        "day_stem_combine_count": {
          "0": 46019520.0,
          "1": 15330354.05,
          "2": 1700880.0,
          "3": 63180.0
        },
        "relation_count": {
          "0": 170580.0,
          "1": 1083960.0,
          "2": 2613120.0,
          "3": 5301300.0,
          "4": 8306340.0,
          "5": 10545130.466667,
          "6": 11904000.0,
          "7": 9899880.0,
          "8": 6542983.583333,
          "9": 3730020.0,
          "10": 1734960.0,
          "11": 710880.0,
          "12": 322380.0,
          "13": 143280.0,
          "14": 48720.0,
          "15": 29520.0,
          "16": 19920.0,
          "17": 6120.0,
          "18": 840.0
        },
        "shensha_count": {
          "0": 6068940.0,
          "1": 15836650.466667,
          "2": 18349920.0,
          "3": 13836583.583333,
          "4": 6659160.0,
          "5": 2031960.0,
          "6": 311880.0,
          "7": 18840.0
        }
      },
      "健康": {
        "missing_element_count": {
          "0": 51313870.466667,
          "1": 11282383.583333,
          "2": 504060.0,
          "3": 13560.0,
          "4": 60.0
        },
        "concentrated_element_count": {
          "0": 78840.0,
          "1": 6674160.0,
          "2": 30176880.0,
          "3": 24320454.05,
          "4": 1862760.0,
          "5": 840.0
        },
        "root_pillar_count": {
          "0": 6006720.0,
          "1": 17914783.583333,
          "2": 21648970.466667,
          "3": 13509240.0,
          "4": 4034220.0
        },
        "pressure_relation_count": {
          "0": 397740.0,
          "1": 2979600.0,
          "2": 6601500.0,
          "3": 12135240.0,
          "4": 14336983.583333,
          "5": 12274450.466667,
          "6": 7272420.0,
          "7": 3693480.0,
          "8": 1842780.0,
          "9": 809160.0,
          "10": 309480.0,
          "11": 194700.0,
          "12": 137880.0,
          "13": 95160.0,
          "14": 29640.0,
          "15": 3720.0
        },
        "repeated_branch_count": {
          "0": 36164263.583333,
          "1": 25745170.466667,
          "2": 1204500.0
        },
        "shensha_count": {
          "0": 1258560.0,
          "1": 5482740.0,
          "2": 10996500.0,
          "3": 14279383.583333,
          "4": 13738320.0,
          "5": 9856860.0,
          "6": 5026930.466667,
          "7": 1887420.0,
          "8": 490020.0,
          "9": 91560.0,
          "10": 5640.0
        }
      }
    }
  },
  "hash": "sha256:0ecc6c5b6c3baee9a647a491121b4f9f97064165658f82f12273963dc73ac9cf"
}
